django_require_migration_name/__init__.py
django_require_migration_name/management/__init__.py
django_require_migration_name/management/commands/makemigrations.py
django_require_migration_name-0.2.0.dist-info/LICENSE
django_require_migration_name-0.2.0.dist-info/WHEEL
django_require_migration_name-0.2.0.dist-info/METADATA
django_require_migration_name-0.2.0.dist-info/RECORD
